nectarchain/__init__.py
nectarchain/_version.py
nectarchain/version.py
nectarchain/data/__init__.py
nectarchain/data/management.py
nectarchain/data/container/__init__.py
nectarchain/data/container/charges_container.py
nectarchain/data/container/core.py
nectarchain/data/container/flatfield_container.py
nectarchain/data/container/gain_container.py
nectarchain/data/container/pedestal_container.py
nectarchain/data/container/waveforms_container.py
nectarchain/data/container/tests/test_charge.py
nectarchain/data/container/tests/test_core_container.py
nectarchain/data/container/tests/test_gain.py
nectarchain/data/container/tests/test_pedestal.py
nectarchain/data/container/tests/test_waveform.py
nectarchain/data/tests/test_management.py
nectarchain/display/__init__.py
nectarchain/display/display.py
nectarchain/dqm/__init__.py
nectarchain/dqm/camera_monitoring.py
nectarchain/dqm/charge_integration.py
nectarchain/dqm/db_utils.py
nectarchain/dqm/dqm_summary_processor.py
nectarchain/dqm/mean_camera_display.py
nectarchain/dqm/mean_waveforms.py
nectarchain/dqm/pixel_participation.py
nectarchain/dqm/pixel_timeline.py
nectarchain/dqm/start_dqm.py
nectarchain/dqm/trigger_statistics.py
nectarchain/dqm/bokeh_app/__init__.py
nectarchain/dqm/bokeh_app/app_hooks.py
nectarchain/dqm/bokeh_app/main.py
nectarchain/dqm/bokeh_app/tests/__init__.py
nectarchain/dqm/bokeh_app/tests/test_app_hooks.py
nectarchain/dqm/tests/test_camera_monitoring.py
nectarchain/dqm/tests/test_charge_integration.py
nectarchain/dqm/tests/test_db_utils.py
nectarchain/dqm/tests/test_mean_camera_display.py
nectarchain/dqm/tests/test_mean_waveforms.py
nectarchain/dqm/tests/test_pixel_participation.py
nectarchain/dqm/tests/test_pixel_timeline.py
nectarchain/dqm/tests/test_trigger_statistics.py
nectarchain/dqm/vm/README.md
nectarchain/dqm/vm/dqm-web-app-ro_cloud-init.yml
nectarchain/dqm/vm/dqm-web-app-rw_cloud-init.yml
nectarchain/makers/__init__.py
nectarchain/makers/charges_makers.py
nectarchain/makers/core.py
nectarchain-0.3.0.dist-info/licenses/LICENSE.md
nectarchain-0.3.0.dist-info/METADATA
nectarchain-0.3.0.dist-info/WHEEL
nectarchain-0.3.0.dist-info/top_level.txt
nectarchain-0.3.0.dist-info/RECORD
