Metadata-Version: 2.4
Name: nectarchain
Version: 0.3.0
Summary: Analysis chain for the CTA MSTN NectarCAM prototype
Author: CTAO NectarCAM collaboration
License: BSD-3-Clause
Project-URL: Bug Tracker, https://github.com/cta-observatory/nectarchain/issues
Project-URL: Source Code, https://github.com/cta-observatory/nectarchain
Classifier: Development Status :: 3 - Alpha
Classifier: License :: OSI Approved :: BSD License
Classifier: Intended Audience :: Science/Research
Classifier: Topic :: Scientific/Engineering :: Astronomy
Classifier: Topic :: Scientific/Engineering :: Physics
Classifier: Programming Language :: Python :: 3 :: Only
Classifier: Programming Language :: Python :: 3.10
Classifier: Programming Language :: Python :: 3.11
Requires-Python: >=3.10
License-File: LICENSE.md
Requires-Dist: ctapipe~=0.24
Requires-Dist: ctapipe-io-nectarcam>0.1
Requires-Dist: bokeh
Requires-Dist: iminuit
Requires-Dist: matplotlib
Requires-Dist: pandas
Requires-Dist: scipy
Requires-Dist: zodb
Requires-Dist: zeo
Requires-Dist: lmfit
Requires-Dist: h5py
Requires-Dist: pyqt5
Requires-Dist: pyqtgraph
Requires-Dist: tomli; python_version < "3.11"
Provides-Extra: test
Requires-Dist: pytest; extra == "test"
Requires-Dist: pytest-cov; extra == "test"
Requires-Dist: pytest-xdist; extra == "test"
Provides-Extra: dev
Requires-Dist: setuptools_scm; extra == "dev"
Provides-Extra: docs
Requires-Dist: sphinx; extra == "docs"
Requires-Dist: sphinx-autodoc-typehints; extra == "docs"
Requires-Dist: sphinx-automodapi; extra == "docs"
Requires-Dist: sphinx-design; extra == "docs"
Requires-Dist: sphinx-qt-documentation; extra == "docs"
Requires-Dist: pydata_sphinx_theme; extra == "docs"
Requires-Dist: numpydoc; extra == "docs"
Provides-Extra: all
Requires-Dist: nectarchain[dev,docs,test]; extra == "all"
Dynamic: license-file
